robust_input.py
robust_input-1.0.1.dist-info/licenses/LICENSE
robust_input-1.0.1.dist-info/METADATA
robust_input-1.0.1.dist-info/WHEEL
robust_input-1.0.1.dist-info/top_level.txt
robust_input-1.0.1.dist-info/RECORD
