Metadata-Version: 2.4
Name: robust-input
Version: 1.0.1
Summary: A very comprehensive terminal input module with no external dependencies
Author-email: tkirkland <tkirkland@users.noreply.github.com>
License: MIT
Keywords: input,terminal,validation,cli,command-line
Classifier: Development Status :: 5 - Production/Stable
Classifier: Intended Audience :: Developers
Classifier: License :: OSI Approved :: MIT License
Classifier: Operating System :: POSIX :: Linux
Classifier: Programming Language :: Python :: 3
Classifier: Programming Language :: Python :: 3.12
Classifier: Topic :: Software Development :: Libraries :: Python Modules
Classifier: Topic :: System :: Shells
Classifier: Topic :: Terminals
Requires-Python: >=3.12
License-File: LICENSE
Provides-Extra: dev
Requires-Dist: black==25.1.0; extra == "dev"
Dynamic: license-file
